sila2_interop_communication_tester/__init__.py
sila2_interop_communication_tester/grpc_stubs/AnyTypeTest_pb2.py
sila2_interop_communication_tester/grpc_stubs/AnyTypeTest_pb2.pyi
sila2_interop_communication_tester/grpc_stubs/AnyTypeTest_pb2_grpc.py
sila2_interop_communication_tester/grpc_stubs/AnyTypeTest_pb2_grpc.pyi
sila2_interop_communication_tester/grpc_stubs/AuthenticationService_pb2.py
sila2_interop_communication_tester/grpc_stubs/AuthenticationService_pb2.pyi
sila2_interop_communication_tester/grpc_stubs/AuthenticationService_pb2_grpc.py
sila2_interop_communication_tester/grpc_stubs/AuthenticationService_pb2_grpc.pyi
sila2_interop_communication_tester/grpc_stubs/AuthenticationTest_pb2.py
sila2_interop_communication_tester/grpc_stubs/AuthenticationTest_pb2.pyi
sila2_interop_communication_tester/grpc_stubs/AuthenticationTest_pb2_grpc.py
sila2_interop_communication_tester/grpc_stubs/AuthenticationTest_pb2_grpc.pyi
sila2_interop_communication_tester/grpc_stubs/AuthorizationService_pb2.py
sila2_interop_communication_tester/grpc_stubs/AuthorizationService_pb2.pyi
sila2_interop_communication_tester/grpc_stubs/AuthorizationService_pb2_grpc.py
sila2_interop_communication_tester/grpc_stubs/AuthorizationService_pb2_grpc.pyi
sila2_interop_communication_tester/grpc_stubs/BasicDataTypesTest_pb2.py
sila2_interop_communication_tester/grpc_stubs/BasicDataTypesTest_pb2.pyi
sila2_interop_communication_tester/grpc_stubs/BasicDataTypesTest_pb2_grpc.py
sila2_interop_communication_tester/grpc_stubs/BasicDataTypesTest_pb2_grpc.pyi
sila2_interop_communication_tester/grpc_stubs/BinaryTransferTest_pb2.py
sila2_interop_communication_tester/grpc_stubs/BinaryTransferTest_pb2.pyi
sila2_interop_communication_tester/grpc_stubs/BinaryTransferTest_pb2_grpc.py
sila2_interop_communication_tester/grpc_stubs/BinaryTransferTest_pb2_grpc.pyi
sila2_interop_communication_tester/grpc_stubs/ErrorHandlingTest_pb2.py
sila2_interop_communication_tester/grpc_stubs/ErrorHandlingTest_pb2.pyi
sila2_interop_communication_tester-0.9.1.dist-info/METADATA
sila2_interop_communication_tester-0.9.1.dist-info/WHEEL
sila2_interop_communication_tester-0.9.1.dist-info/top_level.txt
sila2_interop_communication_tester-0.9.1.dist-info/RECORD
