Metadata-Version: 2.4
Name: sila2-interop-communication-tester
Version: 0.9.1
Author-email: Niklas Mertsch <niklas.mertsch@wega-it.com>
License: MIT License
Requires-Python: >=3.10
Requires-Dist: grpcio
Requires-Dist: lxml
Requires-Dist: protobuf
Requires-Dist: pytest
Requires-Dist: pytest-timeout
Requires-Dist: pytest-html
Requires-Dist: xmlschema
Provides-Extra: dev
Requires-Dist: grpcio-tools; extra == "dev"
Requires-Dist: mypy-protobuf; extra == "dev"
